mhask/__init__.py
mhask-0.0.0.dist-info/LICENSE
mhask-0.0.0.dist-info/METADATA
mhask-0.0.0.dist-info/WHEEL
mhask-0.0.0.dist-info/top_level.txt
mhask-0.0.0.dist-info/RECORD
