Metadata-Version: 2.1
Name: mhask
Version: 0.0.0
Summary: Micropython HTTP Asynchronous Service like Flask
Home-page: https://github.com/damiencorpataux/micropython-mhask
Author: Damien Corpataux
License: MIT
Platform: UNKNOWN
Requires-Dist: micropython-uasyncio
Requires-Dist: micropython-ulogging
